homelab_config/__init__.py
homelab_config/cached.py
homelab_config/core.py
homelab_config/settings.py
homelab_config/utils.py
homelab_config-0.3.0.dist-info/METADATA
homelab_config-0.3.0.dist-info/WHEEL
homelab_config-0.3.0.dist-info/RECORD
