Metadata-Version: 2.4
Name: homelab_config
Version: 0.3.0
Summary: homelab config with consul
Author-email: Shawn Deng <shawndeng1109@qq.com>
License-Expression: MIT
Requires-Python: <3.14,>=3.10
Requires-Dist: diskcache>=5.6.3
Requires-Dist: httpx>=0.25.0
Requires-Dist: loguru>=0.7.3
Requires-Dist: py-consul>=1.6.0
Requires-Dist: pydantic-settings>=2.10.1
Requires-Dist: pydantic>=2.0.0
Requires-Dist: python-hcl2>=4.3.2
Requires-Dist: pyyaml>=6.0.2
Requires-Dist: xmltodict>=0.14.2
Requires-Dist: yarl>=1.20.1
Provides-Extra: dev
Requires-Dist: commitizen>=3.12.0; extra == 'dev'
Requires-Dist: pytest-cov>=6.0.0; extra == 'dev'
Requires-Dist: pytest-mock>=3.14.0; extra == 'dev'
Requires-Dist: pytest>=8.3.4; extra == 'dev'
Requires-Dist: ruff>=0.9.7; extra == 'dev'
Provides-Extra: docs
Requires-Dist: mkdocs-gen-files>=0.5.0; extra == 'docs'
Requires-Dist: mkdocs-literate-nav>=0.6.1; extra == 'docs'
Requires-Dist: mkdocs-material>=9.5.3; extra == 'docs'
Requires-Dist: mkdocs>=1.5.3; extra == 'docs'
Requires-Dist: mkdocstrings-python>=1.7.5; extra == 'docs'
Requires-Dist: mkdocstrings>=0.24.0; extra == 'docs'
Requires-Dist: pymdown-extensions>=10.7; extra == 'docs'
